setup.py
Pseudocode_Pygments_Lexer.egg-info/PKG-INFO
Pseudocode_Pygments_Lexer.egg-info/SOURCES.txt
Pseudocode_Pygments_Lexer.egg-info/dependency_links.txt
Pseudocode_Pygments_Lexer.egg-info/entry_points.txt
Pseudocode_Pygments_Lexer.egg-info/top_level.txt
pseudocode_lexer/__init__.py