Metadata-Version: 1.0
Name: Pseudocode-Pygments-Lexer
Version: 1.0.0
Summary: Pygments Lexer for a french pseudocode
Home-page: UNKNOWN
Author: Simon Wachter
Author-email: simon@wachter.me
License: MIT
Platform: UNKNOWN
